botionplotlib/__init__.py
botionplotlib/core.py
botionplotlib-0.1.0.dist-info/METADATA
botionplotlib-0.1.0.dist-info/WHEEL
botionplotlib-0.1.0.dist-info/top_level.txt
botionplotlib-0.1.0.dist-info/RECORD
