Metadata-Version: 2.2
Name: botionplotlib
Version: 0.1.0
Summary: A beautiful and functional redesign of matplotlib defaults
Home-page: https://github.com/abenstirling/botionplotlib
Author: Ben Stirling
Author-email: ben@abenstirling.com
Project-URL: Bug Tracker, https://github.com/abenstirling/botionplotlib/issues
Classifier: Programming Language :: Python :: 3
Classifier: License :: OSI Approved :: MIT License
Classifier: Operating System :: OS Independent
Classifier: Topic :: Scientific/Engineering :: Visualization
Classifier: Intended Audience :: Science/Research
Classifier: Intended Audience :: Developers
Requires-Python: >=3.6
Requires-Dist: matplotlib>=3.5.0
Requires-Dist: numpy>=1.20.0
Requires-Dist: pillow>=8.0.0
